coinor.cuppy-0.96.2-py3.6-nspkg.pth
coinor/cuppy/__init__.py
coinor/cuppy/cuttingPlanes.py
coinor/cuppy/genericSeparation.py
coinor/cuppy/milpInstance.py
coinor/cuppy/examples/MIP1.py
coinor/cuppy/examples/MIP10.py
coinor/cuppy/examples/MIP2.py
coinor/cuppy/examples/MIP3.py
coinor/cuppy/examples/MIP4.py
coinor/cuppy/examples/MIP5.py
coinor/cuppy/examples/MIP6.py
coinor/cuppy/examples/MIP7.py
coinor/cuppy/examples/MIP8.py
coinor/cuppy/examples/MIP9.py
coinor/cuppy/examples/__init__.py
coinor.cuppy-0.96.2.dist-info/LICENSE
coinor.cuppy-0.96.2.dist-info/METADATA
coinor.cuppy-0.96.2.dist-info/WHEEL
coinor.cuppy-0.96.2.dist-info/namespace_packages.txt
coinor.cuppy-0.96.2.dist-info/top_level.txt
coinor.cuppy-0.96.2.dist-info/RECORD
