Metadata-Version: 2.1
Name: coinor.cuppy
Version: 0.96.2
Summary: Cutting Plane Methods in Python (CuPPy)
Home-page: https://github.com/tkralphs/CuPPy/
Author: Ted Ralphs
Author-email: ted@lehigh.edu
License: Eclipse Public License
Platform: UNKNOWN
Requires-Dist: coinor.grumpy (>=0.95.0)
Requires-Dist: pulp
Requires-Dist: cylp (>=0.9.0)
Requires-Dist: pypolyhedron
